<?xml version="1.0" encoding="UTF-8"?>
<databaseChangeLog
        xmlns="http://www.liquibase.org/xml/ns/dbchangelog"
        xmlns:xsi="http://www.w3.org/2001/XMLSchema-instance"
        xsi:schemaLocation="http://www.liquibase.org/xml/ns/dbchangelog
                      http://www.liquibase.org/xml/ns/dbchangelog/dbchangelog-4.31.xsd"
        objectQuotingStrategy="QUOTE_ONLY_RESERVED_WORDS">

    <changeSet id="1759600649199-1" author="AJ">
        <preConditions onFail="MARK_RAN">
            <not>
                <sequenceExists sequenceName="cart_item_sequence"/>
            </not>
        </preConditions>
        <createSequence incrementBy="50" sequenceName="cart_item_sequence" startValue="1"/>
    </changeSet>

    <changeSet id="1759600649199-2" author="AJ">
        <preConditions onFail="MARK_RAN">
            <not>
                <sequenceExists sequenceName="cart_sequence"/>
            </not>
        </preConditions>
        <createSequence incrementBy="50" sequenceName="cart_sequence" startValue="1"/>
    </changeSet>

    <changeSet id="1759600649199-3" author="AJ">
        <preConditions onFail="MARK_RAN">
            <not>
                <sequenceExists sequenceName="category_sequence"/>
            </not>
        </preConditions>
        <createSequence incrementBy="50" sequenceName="category_sequence" startValue="1000"/>
    </changeSet>

    <changeSet id="1759600649199-4" author="AJ">
        <preConditions onFail="MARK_RAN">
            <not>
                <sequenceExists sequenceName="image_sequence"/>
            </not>
        </preConditions>
        <createSequence incrementBy="1" sequenceName="image_sequence" startValue="1000"/>
    </changeSet>

    <changeSet id="1759600649199-5" author="AJ">
        <preConditions onFail="MARK_RAN">
            <not>
                <sequenceExists sequenceName="person_seq"/>
            </not>
        </preConditions>
        <createSequence incrementBy="50" sequenceName="person_seq" startValue="1"/>
    </changeSet>

    <changeSet id="1759600649199-6" author="AJ">
        <preConditions onFail="MARK_RAN">
            <not>
                <sequenceExists sequenceName="prod_sequence"/>
            </not>
        </preConditions>
        <createSequence incrementBy="50" sequenceName="prod_sequence" startValue="1"/>
    </changeSet>

    <changeSet id="1759600649199-7" author="AJ">
        <preConditions onFail="MARK_RAN">
            <not>
                <sequenceExists sequenceName="revinfo_seq"/>
            </not>
        </preConditions>
        <createSequence incrementBy="50" sequenceName="revinfo_seq" startValue="1"/>
    </changeSet>

    <changeSet id="1759600649199-8" author="AJ">
        <preConditions onFail="MARK_RAN">
            <not>
                <tableExists tableName="address"/>
            </not>
        </preConditions>
        <createTable tableName="address">
            <column autoIncrement="true" name="id" type="BIGINT">
                <constraints nullable="false" primaryKey="true" primaryKeyName="pk_address"/>
            </column>
            <column name="address_type" type="VARCHAR(20)"/>
            <column name="street" type="VARCHAR(255)"/>
            <column name="city" type="VARCHAR(255)"/>
            <column name="state" type="VARCHAR(255)"/>
            <column name="country" type="VARCHAR(255)"/>
            <column name="pin_code" type="VARCHAR(255)"/>
            <column name="person_id" type="BIGINT"/>
        </createTable>
    </changeSet>

    <changeSet id="1759600649199-9" author="AJ">
        <preConditions onFail="MARK_RAN">
            <not>
                <tableExists tableName="cart"/>
            </not>
        </preConditions>
        <createTable tableName="cart">
            <column name="id" type="BIGINT">
                <constraints nullable="false" primaryKey="true" primaryKeyName="pk_cart"/>
            </column>
            <column name="customer_id" type="BIGINT"/>
            <column name="total_price" type="DECIMAL"/>
            <column name="created_by" type="VARCHAR(255)">
                <constraints nullable="false"/>
            </column>
            <column name="created_date" type="timestamp">
                <constraints nullable="false"/>
            </column>
            <column name="last_modified_by" type="VARCHAR(255)"/>
            <column name="last_modified_date" type="timestamp"/>
        </createTable>
    </changeSet>

    <changeSet id="1759600649199-10" author="AJ">
        <preConditions onFail="MARK_RAN">
            <not>
                <tableExists tableName="cart_item"/>
            </not>
        </preConditions>
        <createTable tableName="cart_item">
            <column name="id" type="BIGINT">
                <constraints nullable="false" primaryKey="true" primaryKeyName="pk_cartitem"/>
            </column>
            <column name="cart_id" type="BIGINT">
                <constraints nullable="false"/>
            </column>
            <column name="product_id" type="BIGINT"/>
            <column name="quantity" type="INT"/>
            <column name="price" type="DECIMAL"/>
            <column name="discount" type="DOUBLE">
                <constraints nullable="false"/>
            </column>
            <column name="created_by" type="VARCHAR(255)">
                <constraints nullable="false"/>
            </column>
            <column name="created_date" type="timestamp">
                <constraints nullable="false"/>
            </column>
            <column name="last_modified_by" type="VARCHAR(255)"/>
            <column name="last_modified_date" type="timestamp"/>
        </createTable>
    </changeSet>

    <changeSet id="1759600649199-11" author="AJ">
        <preConditions onFail="MARK_RAN">
            <not>
                <tableExists tableName="cart_item_history"/>
            </not>
        </preConditions>
        <createTable tableName="cart_item_history">
            <column name="rev" type="INT">
                <constraints nullable="false" primaryKey="true" primaryKeyName="pk_cart_item_history"/>
            </column>
            <column name="revtype" type="SMALLINT"/>
            <column name="id" type="BIGINT">
                <constraints nullable="false" primaryKey="true" primaryKeyName="pk_cart_item_history"/>
            </column>
            <column name="cart_id" type="BIGINT"/>
            <column name="product_id" type="BIGINT"/>
            <column name="quantity" type="INT"/>
            <column name="price" type="DECIMAL"/>
            <column name="discount" type="DOUBLE"/>
            <column name="created_by" type="VARCHAR(255)"/>
            <column name="created_date" type="timestamp"/>
            <column name="last_modified_by" type="VARCHAR(255)"/>
            <column name="last_modified_date" type="timestamp"/>
        </createTable>
    </changeSet>

    <changeSet id="1759600649199-12" author="AJ">
        <preConditions onFail="MARK_RAN">
            <not>
                <tableExists tableName="category"/>
            </not>
        </preConditions>
        <createTable tableName="category">
            <column name="id" type="BIGINT">
                <constraints nullable="false" primaryKey="true" primaryKeyName="pk_category"/>
            </column>
            <column name="name" type="VARCHAR(100)">
                <constraints nullable="false"/>
            </column>
            <column name="version" type="INT"/>
            <column name="created_by" type="VARCHAR(255)">
                <constraints nullable="false"/>
            </column>
            <column name="created_date" type="timestamp">
                <constraints nullable="false"/>
            </column>
            <column name="last_modified_by" type="VARCHAR(255)"/>
            <column name="last_modified_date" type="timestamp"/>
        </createTable>
    </changeSet>

    <changeSet id="1759600649199-13" author="AJ">
        <preConditions onFail="MARK_RAN">
            <not>
                <tableExists tableName="customer"/>
            </not>
        </preConditions>
        <createTable tableName="customer">
            <column name="id" type="BIGINT">
                <constraints nullable="false" primaryKey="true" primaryKeyName="pk_customer"/>
            </column>
            <column name="first_name" type="VARCHAR(255)"/>
            <column name="last_name" type="VARCHAR(255)"/>
            <column name="phone" type="varchar(30)"/>
            <column name="user_id" type="BIGINT"/>
            <column name="version" type="INT"/>
            <column name="cart_id" type="BIGINT"/>
            <column name="created_by" type="VARCHAR(255)">
                <constraints nullable="false"/>
            </column>
            <column name="created_date" type="timestamp">
                <constraints nullable="false"/>
            </column>
            <column name="last_modified_by" type="VARCHAR(255)"/>
            <column name="last_modified_date" type="timestamp"/>
        </createTable>
    </changeSet>


    <changeSet id="1759600649199-16" author="AJ">
        <preConditions onFail="MARK_RAN">
            <not>
                <tableExists tableName="image"/>
            </not>
        </preConditions>
        <createTable tableName="image">
            <column name="id" type="BIGINT">
                <constraints nullable="false" primaryKey="true" primaryKeyName="pk_image"/>
            </column>
            <column name="file_name" type="VARCHAR(255)"/>
            <column name="content_type" type="VARCHAR(255)"/>
            <column name="download_url" type="VARCHAR(255)"/>
            <column name="contents" type="bytea">
                <constraints nullable="false"/>
            </column>
            <column name="product_id" type="BIGINT"/>
            <column name="version" type="INT"/>
            <column name="created_by" type="VARCHAR(255)">
                <constraints nullable="false"/>
            </column>
            <column name="created_date" type="timestamp">
                <constraints nullable="false"/>
            </column>
            <column name="last_modified_by" type="VARCHAR(255)"/>
            <column name="last_modified_date" type="timestamp"/>
        </createTable>
    </changeSet>

    <changeSet id="1759600649199-17" author="AJ">
        <preConditions onFail="MARK_RAN">
            <not>
                <tableExists tableName="product"/>
            </not>
        </preConditions>
        <createTable tableName="product">
            <column name="id" type="BIGINT">
                <constraints nullable="false" primaryKey="true" primaryKeyName="pk_product"/>
            </column>
            <column name="name" type="VARCHAR(255)">
                <constraints nullable="false"/>
            </column>
            <column name="description" type="VARCHAR(255)">
                <constraints nullable="false"/>
            </column>
            <column name="price" type="DECIMAL">
                <constraints nullable="false"/>
            </column>
            <column name="discounted_price" type="DECIMAL"/>
            <column name="stock" type="INT"/>
            <column name="category_id" type="BIGINT"/>
            <column name="seller_id" type="BIGINT">
                <constraints nullable="false"/>
            </column>
            <column name="version" type="INT"/>
            <column name="created_by" type="VARCHAR(255)">
                <constraints nullable="false"/>
            </column>
            <column name="created_date" type="timestamp">
                <constraints nullable="false"/>
            </column>
            <column name="last_modified_by" type="VARCHAR(255)"/>
            <column name="last_modified_date" type="timestamp"/>
        </createTable>
    </changeSet>

    <changeSet id="1759600649199-18" author="AJ">
        <preConditions onFail="MARK_RAN">
            <not>
                <tableExists tableName="revinfo"/>
            </not>
        </preConditions>
        <createTable tableName="revinfo">
            <column name="rev" type="INT">
                <constraints nullable="false" primaryKey="true" primaryKeyName="pk_revinfo"/>
            </column>
            <column name="revtstmp" type="BIGINT"/>
        </createTable>
    </changeSet>

    <changeSet id="1759600649199-19" author="AJ">
        <preConditions onFail="MARK_RAN">
            <not>
                <tableExists tableName="role"/>
            </not>
        </preConditions>
        <createTable tableName="role">
            <column autoIncrement="true" name="id" type="BIGINT">
                <constraints nullable="false" primaryKey="true" primaryKeyName="pk_role"/>
            </column>
            <column name="role_name" type="VARCHAR(20)">
                <constraints nullable="false"/>
            </column>
        </createTable>
    </changeSet>

    <changeSet id="1759600649199-20" author="AJ">
        <preConditions onFail="MARK_RAN">
            <not>
                <tableExists tableName="seller"/>
            </not>
        </preConditions>
        <createTable tableName="seller">
            <column name="id" type="BIGINT">
                <constraints nullable="false" primaryKey="true" primaryKeyName="pk_seller"/>
            </column>
            <column name="first_name" type="VARCHAR(255)"/>
            <column name="last_name" type="VARCHAR(255)"/>
            <column name="phone" type="varchar(30)"/>
            <column name="user_id" type="BIGINT"/>
            <column name="version" type="INT"/>
            <column name="created_by" type="VARCHAR(255)">
                <constraints nullable="false"/>
            </column>
            <column name="created_date" type="timestamp">
                <constraints nullable="false"/>
            </column>
            <column name="last_modified_by" type="VARCHAR(255)"/>
            <column name="last_modified_date" type="timestamp"/>
        </createTable>
    </changeSet>

    <changeSet id="1759600649199-21" author="AJ">
        <preConditions onFail="MARK_RAN">
            <not>
                <tableExists tableName="user_role"/>
            </not>
        </preConditions>
        <createTable tableName="user_role">
            <column name="role_id" type="BIGINT">
                <constraints nullable="false" primaryKey="true" primaryKeyName="pk_user_role"/>
            </column>
            <column name="user_id" type="BIGINT">
                <constraints nullable="false" primaryKey="true" primaryKeyName="pk_user_role"/>
            </column>
        </createTable>
    </changeSet>

    <changeSet id="1759600649199-22" author="AJ">
        <preConditions onFail="MARK_RAN">
            <not>
                <tableExists tableName="users"/>
            </not>
        </preConditions>
        <createTable tableName="users">
            <column autoIncrement="true" name="id" type="BIGINT">
                <constraints nullable="false" primaryKey="true" primaryKeyName="pk_users"/>
            </column>
            <column name="username" type="VARCHAR(100)"/>
            <column name="password" type="VARCHAR(100)"/>
            <column name="email" type="VARCHAR(100)"/>
            <column name="enabled" type="BOOLEAN">
                <constraints nullable="false"/>
            </column>
        </createTable>
    </changeSet>

    <changeSet id="1759600649199-23" author="AJ">
        <preConditions onFail="MARK_RAN">
            <not>
                <uniqueConstraintExists tableName="users" constraintName="uc_74165e195b2f7b25de690d14a"/>
            </not>
        </preConditions>
        <addUniqueConstraint columnNames="email" constraintName="uc_74165e195b2f7b25de690d14a" tableName="users"/>
    </changeSet>

    <changeSet id="1759600649199-24" author="AJ">
        <preConditions onFail="MARK_RAN">
            <not>
                <uniqueConstraintExists tableName="users" constraintName="uc_77584fbe74cc86922be2a3560"/>
            </not>
        </preConditions>
        <addUniqueConstraint columnNames="username" constraintName="uc_77584fbe74cc86922be2a3560" tableName="users"/>
    </changeSet>

    <changeSet id="1759600649199-25" author="AJ">
        <preConditions onFail="MARK_RAN">
            <not>
                <uniqueConstraintExists tableName="cart" constraintName="uc_cart_customer"/>
            </not>
        </preConditions>
        <addUniqueConstraint columnNames="customer_id" constraintName="uc_cart_customer" tableName="cart"/>
    </changeSet>

    <changeSet id="1759600649199-26" author="AJ">
        <preConditions onFail="MARK_RAN">
            <not>
                <uniqueConstraintExists tableName="category" constraintName="uc_category_name"/>
            </not>
        </preConditions>
        <addUniqueConstraint columnNames="name" constraintName="uc_category_name" tableName="category"/>
    </changeSet>

    <changeSet id="1759600649199-27" author="AJ">
        <preConditions onFail="MARK_RAN">
            <not>
                <uniqueConstraintExists tableName="customer" constraintName="uc_customer_cart"/>
            </not>
        </preConditions>
        <addUniqueConstraint columnNames="cart_id" constraintName="uc_customer_cart" tableName="customer"/>
    </changeSet>

    <changeSet id="1759600649199-28" author="AJ">
        <preConditions onFail="MARK_RAN">
            <not>
                <uniqueConstraintExists tableName="customer" constraintName="uc_customer_user"/>
            </not>
        </preConditions>
        <addUniqueConstraint columnNames="user_id" constraintName="uc_customer_user" tableName="customer"/>
    </changeSet>

    <changeSet id="1759600649199-29" author="AJ">
        <preConditions onFail="MARK_RAN">
            <not>
                <uniqueConstraintExists tableName="product" constraintName="uc_product_name"/>
            </not>
        </preConditions>
        <addUniqueConstraint columnNames="name" constraintName="uc_product_name" tableName="product"/>
    </changeSet>

    <changeSet id="1759600649199-30" author="AJ">
        <preConditions onFail="MARK_RAN">
            <not>
                <uniqueConstraintExists tableName="role" constraintName="uc_role_role_name"/>
            </not>
        </preConditions>
        <addUniqueConstraint columnNames="role_name" constraintName="uc_role_role_name" tableName="role"/>
    </changeSet>

    <changeSet id="1759600649199-31" author="AJ">
        <preConditions onFail="MARK_RAN">
            <not>
                <uniqueConstraintExists tableName="seller" constraintName="uc_seller_user"/>
            </not>
        </preConditions>
        <addUniqueConstraint columnNames="user_id" constraintName="uc_seller_user" tableName="seller"/>
    </changeSet>

    <changeSet id="1759600649199-32" author="AJ">
        <preConditions onFail="MARK_RAN">
            <not>
                <foreignKeyConstraintExists foreignKeyName="FK_CARTITEM_ON_CART"/>
            </not>
        </preConditions>
        <addForeignKeyConstraint baseColumnNames="cart_id" baseTableName="cart_item"
                                 constraintName="FK_CARTITEM_ON_CART" referencedColumnNames="id"
                                 referencedTableName="cart"/>
    </changeSet>

    <changeSet id="1759600649199-33" author="AJ">
        <preConditions onFail="MARK_RAN">
            <not>
                <foreignKeyConstraintExists foreignKeyName="FK_CARTITEM_ON_PRODUCT"/>
            </not>
        </preConditions>
        <addForeignKeyConstraint baseColumnNames="product_id" baseTableName="cart_item"
                                 constraintName="FK_CARTITEM_ON_PRODUCT" referencedColumnNames="id"
                                 referencedTableName="product"/>
    </changeSet>

    <changeSet id="1759600649199-34" author="AJ">
        <preConditions onFail="MARK_RAN">
            <not>
                <foreignKeyConstraintExists foreignKeyName="FK_CART_ITEM_HISTORY_ON_REV"/>
            </not>
        </preConditions>
        <addForeignKeyConstraint baseColumnNames="rev" baseTableName="cart_item_history"
                                 constraintName="FK_CART_ITEM_HISTORY_ON_REV" referencedColumnNames="rev"
                                 referencedTableName="revinfo"/>
    </changeSet>

    <changeSet id="1759600649199-35" author="AJ">
        <preConditions onFail="MARK_RAN">
            <not>
                <foreignKeyConstraintExists foreignKeyName="FK_CART_ON_CUSTOMER"/>
            </not>
        </preConditions>
        <addForeignKeyConstraint baseColumnNames="customer_id" baseTableName="cart" constraintName="FK_CART_ON_CUSTOMER"
                                 referencedColumnNames="id" referencedTableName="customer"/>
    </changeSet>

    <changeSet id="1759600649199-36" author="AJ">
        <preConditions onFail="MARK_RAN">
            <not>
                <foreignKeyConstraintExists foreignKeyName="FK_CUSTOMER_ON_CART"/>
            </not>
        </preConditions>
        <addForeignKeyConstraint baseColumnNames="cart_id" baseTableName="customer" constraintName="FK_CUSTOMER_ON_CART"
                                 referencedColumnNames="id" referencedTableName="cart"/>
    </changeSet>

    <changeSet id="1759600649199-37" author="AJ">
        <preConditions onFail="MARK_RAN">
            <not>
                <foreignKeyConstraintExists foreignKeyName="FK_CUSTOMER_ON_USER"/>
            </not>
        </preConditions>
        <addForeignKeyConstraint baseColumnNames="user_id" baseTableName="customer" constraintName="FK_CUSTOMER_ON_USER"
                                 referencedColumnNames="id" referencedTableName="users"/>
    </changeSet>

    <changeSet id="1759600649199-38" author="AJ">
        <preConditions onFail="MARK_RAN">
            <not>
                <foreignKeyConstraintExists foreignKeyName="FK_IMAGE_ON_PRODUCT"/>
            </not>
        </preConditions>
        <addForeignKeyConstraint baseColumnNames="product_id" baseTableName="image" constraintName="FK_IMAGE_ON_PRODUCT"
                                 referencedColumnNames="id" referencedTableName="product"/>
    </changeSet>

    <changeSet id="1759600649199-39" author="AJ">
        <preConditions onFail="MARK_RAN">
            <not>
                <foreignKeyConstraintExists foreignKeyName="FK_PRODUCT_ON_CATEGORY"/>
            </not>
        </preConditions>
        <addForeignKeyConstraint baseColumnNames="category_id" baseTableName="product"
                                 constraintName="FK_PRODUCT_ON_CATEGORY" referencedColumnNames="id"
                                 referencedTableName="category"/>
    </changeSet>

    <changeSet id="1759600649199-40" author="AJ">
        <preConditions onFail="MARK_RAN">
            <not>
                <foreignKeyConstraintExists foreignKeyName="FK_PRODUCT_ON_SELLER"/>
            </not>
        </preConditions>
        <addForeignKeyConstraint baseColumnNames="seller_id" baseTableName="product"
                                 constraintName="FK_PRODUCT_ON_SELLER" referencedColumnNames="id"
                                 referencedTableName="seller"/>
    </changeSet>

    <changeSet id="1759600649199-41" author="AJ">
        <preConditions onFail="MARK_RAN">
            <not>
                <foreignKeyConstraintExists foreignKeyName="FK_SELLER_ON_USER"/>
            </not>
        </preConditions>
        <addForeignKeyConstraint baseColumnNames="user_id" baseTableName="seller" constraintName="FK_SELLER_ON_USER"
                                 referencedColumnNames="id" referencedTableName="users"/>
    </changeSet>

    <changeSet id="1759600649199-42" author="AJ">
        <preConditions onFail="MARK_RAN">
            <not>
                <foreignKeyConstraintExists foreignKeyName="fk_user_role_on_role"/>
            </not>
        </preConditions>
        <addForeignKeyConstraint baseColumnNames="role_id" baseTableName="user_role"
                                 constraintName="fk_user_role_on_role" referencedColumnNames="id"
                                 referencedTableName="role"/>
    </changeSet>

    <changeSet id="1759600649199-43" author="AJ">
        <preConditions onFail="MARK_RAN">
            <not>
                <foreignKeyConstraintExists foreignKeyName="fk_user_role_on_user"/>
            </not>
        </preConditions>
        <addForeignKeyConstraint baseColumnNames="user_id" baseTableName="user_role"
                                 constraintName="fk_user_role_on_user" referencedColumnNames="id"
                                 referencedTableName="users"/>
    </changeSet>

</databaseChangeLog>